spreadsheet_dl/__init__.py
spreadsheet_dl/_version.py
spreadsheet_dl/adapters.py
spreadsheet_dl/ai_export.py
spreadsheet_dl/ai_training.py
spreadsheet_dl/backup.py
spreadsheet_dl/builder.py
spreadsheet_dl/charts.py
spreadsheet_dl/cli.py
spreadsheet_dl/completions.py
spreadsheet_dl/config.py
spreadsheet_dl/exceptions.py
spreadsheet_dl/export.py
spreadsheet_dl/interactive.py
spreadsheet_dl/mcp_server.py
spreadsheet_dl/notifications.py
spreadsheet_dl/ods_editor.py
spreadsheet_dl/path_security.py
spreadsheet_dl/performance.py
spreadsheet_dl/plugins.py
spreadsheet_dl/progress.py
spreadsheet_dl/py.typed
spreadsheet_dl/renderer.py
spreadsheet_dl/security.py
spreadsheet_dl/serialization.py
spreadsheet_dl/streaming.py
spreadsheet_dl/visualization.py
spreadsheet_dl/webdav_upload.py
spreadsheet_dl/xlsx_renderer.py
spreadsheet_dl/_builder/__init__.py
spreadsheet_dl/_builder/core.py
spreadsheet_dl/_builder/exceptions.py
spreadsheet_dl/_builder/formulas.py
spreadsheet_dl/_builder/models.py
spreadsheet_dl/_builder/references.py
spreadsheet_dl/_cli/__init__.py
spreadsheet_dl/_cli/app.py
spreadsheet_dl/_cli/commands.py
spreadsheet_dl/_cli/utils.py
spreadsheet_dl/_mcp/__init__.py
spreadsheet_dl/_mcp/cli.py
spreadsheet_dl/_mcp/config.py
spreadsheet_dl/_mcp/exceptions.py
spreadsheet_dl/_mcp/handlers.py
spreadsheet_dl/_mcp/models.py
spreadsheet_dl/_mcp/registry.py
spreadsheet_dl/_mcp/server.py
spreadsheet_dl/_mcp/tools/__init__.py
spreadsheet_dl/_mcp/tools/analysis_tools.py
spreadsheet_dl/_mcp/tools/chart_tools.py
spreadsheet_dl/_mcp/tools/export_tools.py
spreadsheet_dl/_mcp/tools/spreadsheet_tools.py
spreadsheet_dl/_mcp/tools/style_tools.py
spreadsheet_dl/_mcp/tools/template_tools.py
spreadsheet_dl/builders/__init__.py
spreadsheet_dl/builders/conditional.py
spreadsheet_dl/builders/style.py
spreadsheet_dl/builders/validation.py
spreadsheet_dl/domains/__init__.py
spreadsheet_dl/domains/base.py
spreadsheet_dl/domains/biology/__init__.py
spreadsheet_dl/domains/biology/plugin.py
spreadsheet_dl-0.1.0.dist-info/METADATA
spreadsheet_dl-0.1.0.dist-info/WHEEL
spreadsheet_dl-0.1.0.dist-info/entry_points.txt
spreadsheet_dl-0.1.0.dist-info/licenses/LICENSE
spreadsheet_dl-0.1.0.dist-info/RECORD
