Metadata-Version: 2.4
Name: spreadsheet-dl
Version: 0.1.0
Summary: Universal spreadsheet definition language. Define once in Python or YAML, export to ODS/XLSX/PDF. Domain plugins for science, engineering, finance. Native MCP server for AI integration.
Project-URL: Homepage, https://github.com/lair-click-bats/spreadsheet-dl
Project-URL: Documentation, https://lair-click-bats.github.io/spreadsheet-dl/
Project-URL: Repository, https://github.com/lair-click-bats/spreadsheet-dl
Project-URL: Issues, https://github.com/lair-click-bats/spreadsheet-dl/issues
Project-URL: Changelog, https://github.com/lair-click-bats/spreadsheet-dl/blob/main/CHANGELOG.md
Author: lair-click-bats
License: MIT
License-File: LICENSE
Keywords: ai,ai-integration,automation,biology,budget,builder,builder-pattern,chart,chemistry,civil-engineering,claude,data-science,declarative,declarative-api,definition-language,dsl,education,electrical-engineering,engineering,excel,finance,fluent-api,formula,libreoffice,llm,machine-learning,manufacturing,mcp,mcp-server,mechanical-engineering,model-context-protocol,multi-format,ods,pdf,physics,report-generation,scientific-computing,spreadsheet,statistics,template,theme,universal,xlsx,yaml
Classifier: Development Status :: 4 - Beta
Classifier: Intended Audience :: Developers
Classifier: Intended Audience :: Financial and Insurance Industry
Classifier: Intended Audience :: Manufacturing
Classifier: Intended Audience :: Science/Research
Classifier: License :: OSI Approved :: MIT License
Classifier: Programming Language :: Python :: 3
Classifier: Programming Language :: Python :: 3.12
Classifier: Programming Language :: Python :: 3.13
Classifier: Topic :: Office/Business :: Financial :: Spreadsheet
Classifier: Topic :: Scientific/Engineering
Classifier: Topic :: Software Development :: Libraries :: Python Modules
Classifier: Topic :: Text Processing :: Markup
Classifier: Typing :: Typed
Requires-Python: >=3.12
Requires-Dist: odfpy>=1.4.1
Requires-Dist: pandas>=2.1.0
Requires-Dist: pyexcel-ods3>=0.6.1
Requires-Dist: requests>=2.31.0
Requires-Dist: rich>=13.0.0
Provides-Extra: all
Requires-Dist: beautifulsoup4>=4.12.0; extra == 'all'
Requires-Dist: cryptography>=42.0.0; extra == 'all'
Requires-Dist: defusedxml>=0.7.0; extra == 'all'
Requires-Dist: lxml>=5.0.0; extra == 'all'
Requires-Dist: openpyxl>=3.1.0; extra == 'all'
Requires-Dist: pyyaml>=6.0.0; extra == 'all'
Requires-Dist: reportlab>=4.0.0; extra == 'all'
Provides-Extra: config
Requires-Dist: pyyaml>=6.0.0; extra == 'config'
Provides-Extra: dev
Requires-Dist: hypothesis>=6.100.0; extra == 'dev'
Requires-Dist: mypy>=1.13.0; extra == 'dev'
Requires-Dist: pandas-stubs>=2.1.0; extra == 'dev'
Requires-Dist: pytest-cov>=4.1.0; extra == 'dev'
Requires-Dist: pytest>=8.0.0; extra == 'dev'
Requires-Dist: ruff>=0.8.0; extra == 'dev'
Requires-Dist: towncrier>=24.8.0; extra == 'dev'
Requires-Dist: types-beautifulsoup4>=4.12.0; extra == 'dev'
Requires-Dist: types-pyyaml>=6.0.0; extra == 'dev'
Requires-Dist: types-requests>=2.31.0; extra == 'dev'
Provides-Extra: docs
Requires-Dist: interrogate>=1.7.0; extra == 'docs'
Requires-Dist: mike>=2.1.0; extra == 'docs'
Requires-Dist: mkdocs-gen-files>=0.5.0; extra == 'docs'
Requires-Dist: mkdocs-literate-nav>=0.6.0; extra == 'docs'
Requires-Dist: mkdocs-material>=9.5.0; extra == 'docs'
Requires-Dist: mkdocs-section-index>=0.3.8; extra == 'docs'
Requires-Dist: mkdocs>=1.6.0; extra == 'docs'
Requires-Dist: mkdocstrings[python]>=0.27.0; extra == 'docs'
Provides-Extra: export
Requires-Dist: openpyxl>=3.1.0; extra == 'export'
Requires-Dist: reportlab>=4.0.0; extra == 'export'
Provides-Extra: html
Requires-Dist: beautifulsoup4>=4.12.0; extra == 'html'
Requires-Dist: lxml>=5.0.0; extra == 'html'
Provides-Extra: mcp
Provides-Extra: notifications
Provides-Extra: plaid
Requires-Dist: plaid-python>=16.0.0; extra == 'plaid'
Provides-Extra: security
Requires-Dist: cryptography>=42.0.0; extra == 'security'
Requires-Dist: defusedxml>=0.7.0; extra == 'security'
Provides-Extra: visualization
